Metadata-Version: 2.4
Name: twscrape_fix
Version: 0.16.0
Summary: Twitter GraphQL and Search API implementation with SNScrape data models
Project-URL: repository, https://github.com/vladkens/twscrape
Author-email: yukimoto <shtomcom@gmail.com>
License: MIT
License-File: LICENSE
Keywords: api,scrape,scrapper,snscrape,twitter
Classifier: Development Status :: 4 - Beta
Classifier: License :: OSI Approved :: MIT License
Classifier: Programming Language :: Python :: 3.10
Classifier: Programming Language :: Python :: 3.11
Classifier: Programming Language :: Python :: 3.12
Classifier: Programming Language :: Python :: 3.13
Requires-Python: >=3.10
Requires-Dist: aiosqlite>=0.17.0
Requires-Dist: fake-useragent>=1.4.0
Requires-Dist: httpx>=0.26.0
Requires-Dist: loguru>=0.7.0
Requires-Dist: pyotp>=2.9.0
Provides-Extra: dev
Requires-Dist: build>=1.2.2; extra == 'dev'
Requires-Dist: pyright>=1.1.369; extra == 'dev'
Requires-Dist: pytest-asyncio>=0.23.3; extra == 'dev'
Requires-Dist: pytest-cov>=4.1.0; extra == 'dev'
Requires-Dist: pytest-httpx>=0.28.0; extra == 'dev'
Requires-Dist: pytest>=7.4.4; extra == 'dev'
Requires-Dist: ruff>=0.1.11; extra == 'dev'
